LICENSE.md
README.md
setup.py
sisaptools/__init__.py
sisaptools/aes.py
sisaptools/constants.py
sisaptools/database.py
sisaptools/lvclient.py
sisaptools/mail.py
sisaptools/redis.py
sisaptools/services.json
sisaptools/services.py
sisaptools/ssh.py
sisaptools/textfile.py
sisaptools/trello.py
sisaptools.egg-info/PKG-INFO
sisaptools.egg-info/SOURCES.txt
sisaptools.egg-info/dependency_links.txt
sisaptools.egg-info/requires.txt
sisaptools.egg-info/top_level.txt