Metadata-Version: 2.1
Name: sisaptools
Version: 1.17.3
Summary: Eines comunes de SISAP
Home-page: https://github.com/sisap-ics/sisaptools
Author: SISAP
Author-email: sisap@gencat.cat
License: MIT
Keywords: sisap database development
Platform: UNKNOWN
Classifier: Development Status :: 5 - Production/Stable
Classifier: Intended Audience :: Developers
Classifier: Topic :: Software Development :: Build Tools
Classifier: License :: OSI Approved :: MIT License
Classifier: Programming Language :: Python :: 2
Classifier: Programming Language :: Python :: 3
License-File: LICENSE.md
